diefpy/__init__.py
diefpy/dief.py
diefpy/radaraxes.py
diefpy/data/metrics.csv
diefpy/data/traces.csv
diefpy-1.2.1.dist-info/LICENSE
diefpy-1.2.1.dist-info/METADATA
diefpy-1.2.1.dist-info/WHEEL
diefpy-1.2.1.dist-info/top_level.txt
diefpy-1.2.1.dist-info/RECORD
