Metadata-Version: 2.1
Name: diefpy
Version: 1.2.1
Summary: Python package for computing diefficiency metrics dief@t and dief@k.
Home-page: https://github.com/SDM-TIB/diefpy
Download-URL: https://github.com/SDM-TIB/diefpy/archive/refs/tags/v1.2.1.tar.gz
Author: Philipp D. Rohde, Nikoleta Themeliotou
Author-email: philipp.rohde@tib.eu
License: MIT
Project-URL: Bug Tracker, https://github.com/SDM-TIB/diefpy/issues
Keywords: metrics benchmarking efficiency diefficiency-metrics dief python
Classifier: Development Status :: 5 - Production/Stable
Classifier: Framework :: Matplotlib
Classifier: Programming Language :: Python
Classifier: Programming Language :: Python :: 3
Classifier: Programming Language :: Python :: 3 :: Only
Classifier: Programming Language :: Python :: 3.7
Classifier: Programming Language :: Python :: 3.8
Classifier: Programming Language :: Python :: 3.9
Classifier: Programming Language :: Python :: 3.10
Classifier: Programming Language :: Python :: 3.11
Classifier: License :: OSI Approved :: MIT License
Classifier: Operating System :: OS Independent
Classifier: Topic :: System :: Benchmark
Classifier: Typing :: Typed
Requires-Python: >=3.7
License-File: LICENSE
Requires-Dist: matplotlib (>=3.2.2)
Requires-Dist: numpy (>=1.8.0)
